[
    {
      "state": {
        "name": "Abia State",
        "capital":"Umuahia",
        "id": 1
      }
    },
  
    {
      "state": {
        "name": "Adamawa State",
        "capital":"Yola",
        "id": 2
      }
    },
  
    {
      "state": {
        "name": "Akwa Ibom State",
        "capital":"Uyo",
        "id": 3
      }
    },
  
    {
      "state": {
        "name": "Anambra State",
        "capital":"Awka",
        "id": 4
      }
    },
  
    {
      "state": {
        "name": "Bauchi State",
        "capital":"Bauchi",
        "id": 5
      }
    },
  
    {
      "state": {
        "name": "Bayelsa State",
        "capital":"Yenegoa",
        "id": 6
      }
    },
  
    {
      "state": {
        "name": "Benue State",
        "capital":"Makurdi",
        "id": 7
      }
    },
  
    {
      "state": {
        "name": "Borno State",
        "capital":"Maiduguri",
        "id": 8
      }
    },
  
    {
      "state": {
        "name": "Cross River State",
        "capital":"Calabar",
        "id": 9
      }
    },
  
    {
      "state": {
        "name": "Delta State",
        "capital":"Asaba",
        "id": 10
      }
    },
  
    {
      "state": {
        "name": "Ebonyi State",
        "capital":"Abakaliki",
        "id": 11
      }
    },
  
    {
      "state": {
        "name": "Edo State",
        "capital":"Benin City",
        "id": 12
      }
    },
  
    {
      "state": {
        "name": "Ekiti State",
        "capital":"Ado-Ekiti",
        "id": 13
      }
    },
  
    {
      "state": {
        "name": "Enugu State",
        "capital":"Enugu",
        "id": 14
      }
    },
  
    {
      "state": {
        "name": "FCT",
        "capital":"Abuja",
        "id": 15
      }
    },
  
    {
      "state": {
        "name": "Gombe State",
        "capital":"Gombe",
        "id": 16
      }
    },
  
    {
      "state": {
        "name": "Imo State",
        "capital":"Owerri",
        "id": 17
      }
    },
  
    {
      "state": {
        "name": "Jigawa State",
        "capital":"Dutse",
        "id": 18
      }
    },
  
    {
      "state": {
        "name": "Kaduna State",
        "capital":"Kaduna",
        "id": 19
      }
    },
  
    {
      "state": {
        "name": "Kano State",
        "capital":"Kano",
        "id": 20
      }
    },
  
    {
      "state": {
        "name": "Katsina State",
        "capital":"Katsina",
        "id": 21
      }
    },
  
    {
      "state": {
        "name": "Kebbi State",
        "capital":"Birni Kebbi",
        "id": 22
      }
    },
  
    {
      "state": {
        "name": "Kogi State",
        "capital":"Lokoja",
        "id": 23
      }
    },
  
    {
      "state": {
        "name": "Kwara State",
        "capital":"Ilorin",
        "id": 24
      }
    },
  
    {
      "state": {
        "name": "Lagos State",
        "capital":"Ikeja",
        "id": 25
      }
    },
  
    {
      "state": {
        "name": "Nasarawa State",
        "capital":"Lafia",
        "id": 26
      }
    },
  
    {
      "state": {
        "name": "Niger State",
        "capital":"Minna",
        "id": 27
      }
    },
  
    {
      "state": {
        "name": "Ogun State",
        "capital":"Abeokuta",
        "id": 28
      }
    },
  
    {
      "state": {
        "name": "Ondo State",
        "capital":"Akure",
        "id": 29
      }
    },
  
    {
      "state": {
        "name": "Osun State",
        "capital":"Oshogbo",
        "id": 30
      }
    },
  
    {
      "state": {
        "name": "Oyo State",
        "capital":"Ibadan",
        "id": 31
      }
    },
  
    {
      "state": {
        "name": "Plateau State",
        "capital":"Jos",
        "id": 32
      }
    },
  
    {
      "state": {
        "name": "Rivers State",
        "capital":"Port Harcourt",
        "id": 33
      }
    },
  
    {
      "state": {
        "name": "Sokoto State",
        "capital":"Sokoto",
        "id": 34
      }
    },
  
    {
      "state": {
        "name": "Taraba State",
        "capital":"Jalingo",
        "id": 35
      }
    },
  
    {
      "state": {
        "name": "Yobe State",
        "capital":"Damaturu",
        "id": 36
      }
    },
  
    {
      "state": {
        "name": "Zamfara State",
        "capital":"Guasau",
        "id": 37
      }
    }
  ]
  